readpaf.py
readpaf-0.0.10.dist-info/LICENSE
readpaf-0.0.10.dist-info/METADATA
readpaf-0.0.10.dist-info/WHEEL
readpaf-0.0.10.dist-info/top_level.txt
readpaf-0.0.10.dist-info/RECORD
