Metadata-Version: 2.1
Name: readpaf
Version: 0.0.10
Summary: minimap2 PAF file reader
Home-page: https://github.com/alexomics/read-paf
Author: Alexander Payne
Author-email: alexander.payne@nottingham.ac.uk
License: MIT
Project-URL: Bug Tracker, https://github.com/alexomics/read-paf/issues
Project-URL: Source Code, https://github.com/alexomics/read-paf
Platform: OS Independent
Classifier: Development Status :: 3 - Alpha
Classifier: License :: OSI Approved :: MIT License
Classifier: Operating System :: OS Independent
Classifier: Intended Audience :: Developers
Classifier: Intended Audience :: Science/Research
Classifier: Programming Language :: Python
Classifier: Programming Language :: Python :: 2
Classifier: Programming Language :: Python :: 2.7
Classifier: Programming Language :: Python :: 3
Classifier: Programming Language :: Python :: 3.5
Classifier: Programming Language :: Python :: 3.6
Classifier: Programming Language :: Python :: 3.7
Classifier: Programming Language :: Python :: 3.8
Classifier: Programming Language :: Python :: 3.9
Classifier: Topic :: Scientific/Engineering :: Bio-Informatics
Requires-Python: >=2.7, !=3.0.*, !=3.1.*, !=3.2.*, !=3.3.*, !=3.4.*
License-File: LICENSE
Provides-Extra: pandas
Requires-Dist: pandas ; extra == 'pandas'
